{
    "npcName": "Sally",
    "dialogueLines": [
        {
            "text": "Hey! What do you think of my new hair?",
            "requiredMorality": 0,
            "choices": [
                {
                  "npcName": "Sarah",
                    "text": "Oh em gee, I love it!",
                    "nextIndex": 1,
                    "moralityChange": 1
                },
                {
                  "npcName": "Sarah",
                    "text": "Honestly, I don't think it suits you.",
                    "nextIndex": 1,
                    "moralityChange": -1
                }
            ]
        },
        {
          "npcName": "Sally",
            "text": "Yay! Thanks!",
            "requiredMorality": 1,
            "choices": []
        },
        {
          "npcName": "Sally",
            "text": "Wow. I was trying something new...whatever.",
            "requiredMorality": -1,
            "choices": []
        }
    ]
}

