{
    "npcName": "Sarah",
    "dialogueLines": [
        {
            "text": "Hey! Thoughts on my new outfit?",
            "requiredMorality": 0,
            "choices": [
                {
                  "npcName": "Sally",
                    "text": "(Gasps) You look so good!",
                    "nextIndex": 1,
                    "moralityChange": 1
                },
                {
                  "npcName": "Sally",
                    "text": "Sorry, but I wouldn't be caught dead wearing that.",
                    "nextIndex": 1,
                    "moralityChange": -1
                }
            ]
        },
        {
          "npcName": "Sarah",
            "text": "Thank you, sweetie!",
            "requiredMorality": 1,
            "choices": []
        },
        {
          "npcName": "Sarah",
            "text": "Well what do you know about...whatever.",
            "requiredMorality": -1,
            "choices": []
        }
    ]
}

