{"inkVersion":21,"root":[["\n",{"->":"main"},["done",{"#f":5,"#n":"g-0"}],null],"done",{"main":[["^Hi my name is Irene","\n","ev","str","^This is the the good answer.","/str","/ev",{"*":".^.c-0","flg":20},"ev","str","^This is the bad answer.","/str","/ev",{"*":".^.c-1","flg":20},"ev","str","^This is the Nutral answer.","/str","/ev",{"*":".^.c-2","flg":20},{"c-0":["\n","ev",{"VAR?":"Morality"},1,"+",{"VAR=":"Morality","re":true},"/ev",{"->":"goodResponse"},{"#f":5}],"c-1":["\n","ev",{"VAR?":"Morality"},1,"-",{"VAR=":"Morality","re":true},"/ev",{"->":"badResponse"},{"#f":5}],"c-2":["\n","ev",{"VAR?":"Morality"},0,"+",{"VAR=":"Morality","re":true},"/ev",{"->":"neutralResponse"},{"#f":5}]}],{"#f":1}],"goodResponse":["^This means you picked the good response.","\n","end",{"#f":1}],"badResponse":["^This means you picked the bad response.","\n","end",{"#f":1}],"neutralResponse":["^This means you picked the nutral response.","\n","end",{"#f":1}],"global decl":["ev",0,{"VAR=":"Morality"},"/ev","end",null],"#f":1}],"listDefs":{}}